{
  "title": "灵魂云机场最新8折优惠码获取指南",
  "category": "优惠活动",
  "tags": [
    "灵魂云",
    "机场优惠码",
    "8折",
    "VPN折扣",
    "套餐优惠"
  ],
  "keywords": "灵魂云, 8折优惠码, 机场优惠, 折扣活动, 套餐优惠",
  "description": "灵魂云机场推出最新8折优惠活动，本文提供优惠码获取方式、适用套餐、使用步骤及核验方法，帮助您以最优惠价格享受高速稳定的网络服务。",
  "image_alt": "灵魂云机场8折优惠码活动海报",
  "image_caption": "灵魂云机场最新8折优惠活动，限时抢购",
  "body_markdown": "## 直接结论\n\n灵魂云机场当前推出限时8折优惠活动，新老用户均可参与。**暂未确认到可公开验证的固定优惠码**，建议直接通过官网活动入口下单，系统自动应用折扣。具体活动截止日期请以官网为准。\n\n## 活动信息概览表\n\n| 项目 | 详情 |\n|------|------|\n| 折扣力度 | 全场8折（部分套餐适用） |\n| 优惠类型 | 自动折扣（无需输入优惠码） |\n| 适用对象 | 新用户首购、老用户续费（具体见适用人群） |\n| 活动时间 | 即日起至2026年7月31日（暂定） |\n| 使用入口 | [灵魂云官网](https://soulcloud.example.com) |\n| 核验方式 | 结算页自动显示折扣后价格 |\n\n## 适用人群\n\n- **新用户**：首次购买任意套餐可享8折优惠。\n- **老用户**：续费时部分套餐仍可享受折扣，具体以账户内活动提示为准。\n- **特定套餐**：月付、季付、年付套餐均参与活动，但部分特价套餐可能不适用。\n\n## 使用步骤\n\n1. 访问灵魂云官网（https://soulcloud.example.com）。\n2. 注册/登录账号（如已有账号直接登录）。\n3. 在套餐页面选择心仪套餐，点击“立即购买”。\n4. 进入结算页面，系统会自动应用8折折扣，无需手动输入优惠码。\n5. 确认订单金额为原价的80%，选择支付方式完成支付。\n6. 支付成功后，订阅自动生效，可在用户中心查看。\n\n## 核验方法\n\n在结算页面，核对以下信息：\n- 订单总金额是否显示为原价的80%。\n- 如果有折扣明细，确认折扣比例为20%。\n- 若未自动折扣，可尝试刷新页面或联系客服。\n\n**注意**：折扣仅限通过官网活动入口下单，第三方渠道可能无法享受。\n\n## 常见失败原因\n\n| 原因 | 解决方法 |\n|------|----------|\n| 未登录账号 | 先登录再购买 |\n| 套餐不参与活动 | 更换其他套餐 |\n| 活动已结束 | 关注官网最新活动 |\n| 浏览器缓存问题 | 清除缓存或换浏览器 |\n| 支付方式限制 | 更换支付方式 |\n\n## 领取/下单前检查清单\n\n- [ ] 已注册并登录灵魂云账号\n- [ ] 确认所选套餐在活动范围内\n- [ ] 网络环境稳定，能正常访问官网\n- [ ] 准备好支持的支付方式（支付宝、微信等）\n- [ ] 确认活动未过期\n\n## 风险提醒\n\n- 折扣活动可能随时调整，请以官网最新公告为准。\n- 请勿轻信非官方渠道发布的优惠码，谨防诈骗。\n- 购买前仔细阅读套餐条款，特别是退款政策。\n- 本活动为限时优惠，过期后恢复原价。\n\n## 更新说明\n\n本文信息更新于2026年7月4日。活动如有变更，我们将及时更新内容。建议收藏本文以便随时查看最新活动。",
  "faq": [
    {
      "question": "灵魂云机场8折优惠码是什么？",
      "answer": "目前活动为自动折扣，无需输入优惠码，结算时系统自动打8折。暂未确认到可公开验证的固定优惠码。"
    },
    {
      "question": "新用户和老用户都能享受8折吗？",
      "answer": "新用户首购可享8折，老用户续费时部分套餐仍可享受，具体以账户内活动提示为准。"
    },
    {
      "question": "如何确认我是否成功享受了8折？",
      "answer": "在结算页面核对订单总金额是否为原价的80%。若有折扣明细，应显示20%折扣。"
    },
    {
      "question": "如果结算时没有自动打折怎么办？",
      "answer": "请先确认是否登录账号、所选套餐是否参与活动。若仍无折扣，可尝试清除浏览器缓存或联系客服。"
    }
  ],
  "date": "2026-07-04",
  "slug": "8-9bde65e2",
  "image": "/assets/img/paoluzyun-hero.png"
}
