{
  "title": "白月光机场最新8折优惠码获取指南：活动详情与核验说明",
  "category": "优惠活动",
  "tags": [
    "白月光机场",
    "优惠码",
    "8折",
    "套餐折扣",
    "VPN优惠"
  ],
  "keywords": "白月光机场优惠码, 8折优惠, 机场折扣, 套餐活动, 优惠码核验",
  "description": "白月光机场最新8折优惠码获取与使用全攻略。本文提供活动概览、适用人群、使用步骤、核验方法及常见失败原因，助你顺利享受折扣。",
  "image_alt": "白月光机场8折优惠活动宣传图",
  "image_caption": "白月光机场8折优惠，限时活动，详情请查看官网。",
  "body_markdown": "## 直接结论\n\n白月光机场目前推出8折优惠活动，但暂未确认到可公开验证的固定优惠码。建议通过官网活动入口直接下单，系统可能自动应用折扣或提供新用户专属优惠。请在结算页面仔细核对最终价格，确认折扣生效后再付款。\n\n## 活动信息概览表\n\n| 项目 | 内容 |\n|------|------|\n| 折扣类型 | 套餐折扣（非固定优惠码） |\n| 折扣力度 | 约8折（具体以套餐原价为准） |\n| 活动时间 | 2026-06-18起，截止日期待官网公告 |\n| 适用套餐 | 月付/季付/年付套餐（部分特价套餐除外） |\n| 优惠码 | 暂未确认到可公开验证的固定优惠码 |\n| 自动折扣 | 部分套餐直接显示折扣价，无需输入码 |\n| 新用户活动 | 新用户首单可能额外享有折扣，详见官网 |\n\n## 适用人群\n\n- 首次购买白月光机场服务的新用户\n- 需要续费的老用户（关注套餐续费折扣）\n- 追求性价比、希望长期使用稳定机场的用户\n\n## 使用步骤\n\n1. **访问官网**：打开白月光机场官方网站（请认准官方域名）。\n2. **选择套餐**：浏览套餐列表，注意标有“折扣”或“优惠”字样的套餐。\n3. **进入结算页**：点击“立即购买”或“订阅”，进入结算页面。\n4. **输入优惠码（如有）**：若你持有官方发布的优惠码，在“优惠码”输入框中填写。若没有，跳过此步。\n5. **核对价格**：确认最终支付金额是否已折扣。原价与折扣价应明显不同。\n6. **完成支付**：选择支付方式，完成付款。\n\n## 核验方法\n\n- **在结算页面直接查看**：折扣后的价格会直接显示，对比原价即可。\n- **查看订单详情**：支付后，在个人中心查看订单，确认实付金额。\n- **联系客服**：如对折扣有疑问，联系官方客服核实。\n\n## 常见失败原因\n\n| 失败原因 | 说明 |\n|----------|------|\n| 优惠码无效 | 输入的优惠码已过期、不存在或已达使用次数上限 |\n| 套餐不适用 | 所选套餐不在活动范围内（如特价套餐） |\n| 新老用户限制 | 活动仅限新用户，老用户无法享受 |\n| 未达到条件 | 部分活动要求最低购买时长或金额 |\n| 系统错误 | 网络或平台问题导致折扣未应用，可联系客服 |\n\n## 领取/下单前检查清单\n\n- [ ] 确认活动仍在有效期内（参考官网公告）\n- [ ] 确认所选套餐参与折扣活动\n- [ ] 如有优惠码，确认来源可靠且未过期\n- [ ] 检查结算页价格是否已折扣\n- [ ] 阅读活动条款，了解限制条件\n\n## 风险提醒\n\n- 任何要求私下转账、非官方渠道购买的行为均存在风险，请认准官网。\n- 优惠码可能随时失效，请以结算页实际价格为准。\n- 请勿轻信非官方发布的“内部优惠码”，谨防诈骗。\n- 本活动最终解释权归白月光机场所有。\n\n## 更新说明\n\n本文基于2026-06-18的活动信息编写。优惠活动可能随时调整，建议关注官网最新公告。如发现优惠码或折扣有变，我们将及时更新。",
  "faq": [
    {
      "question": "白月光机场有8折优惠码吗？",
      "answer": "目前暂未确认到可公开验证的固定优惠码，但官网部分套餐直接显示8折折扣价，无需输入码即可享受。建议在结算页直接查看最终价格。"
    },
    {
      "question": "如何确认优惠是否生效？",
      "answer": "在结算页面，系统会显示原价和折扣后的价格。支付后可在个人中心查看订单详情，核对实付金额。如有疑问，联系客服确认。"
    },
    {
      "question": "老用户能享受8折优惠吗？",
      "answer": "部分活动可能仅限新用户，但老用户续费时也可能有专属折扣。请登录账号查看续费价格，或关注官网活动公告。"
    },
    {
      "question": "优惠活动持续到什么时候？",
      "answer": "活动自2026-06-18开始，具体截止日期请以白月光机场官网公告为准。建议尽早下单，以免错过优惠。"
    }
  ],
  "date": "2026-06-18",
  "slug": "8-1fb3d7e8",
  "image": "/assets/img/paoluzyun-hero.png"
}
