{
  "title": "IPLC机场最新8折优惠码获取指南（2026-06-19更新）",
  "category": "优惠活动",
  "tags": [
    "IPLC机场",
    "优惠码",
    "8折",
    "折扣活动",
    "套餐优惠",
    "使用教程"
  ],
  "keywords": "IPLC机场优惠码, IPLC机场8折, IPLC机场折扣, IPLC机场套餐, IPLC机场优惠活动",
  "description": "本文汇总IPLC机场最新8折优惠码获取方式、活动详情、使用步骤及核验方法。暂未确认到可公开验证的固定优惠码，建议关注官网活动或新用户自动折扣。提供完整检查清单和常见失败原因，助你顺利享受优惠。",
  "image_alt": "IPLC机场8折优惠码活动宣传图",
  "image_caption": "IPLC机场8折优惠码活动，限时折扣，新老用户均可参与。",
  "body_markdown": "## 直接结论\n\n截至2026年6月19日，暂未确认到可公开验证的固定优惠码。不过，IPLC机场目前针对新用户提供自动折扣（如首月8折），部分套餐也有限时直降活动。建议直接在官网结算页查看是否自动应用折扣，或关注官方公告获取最新优惠码。\n\n## 活动信息概览表\n\n| 活动类型 | 折扣力度 | 适用对象 | 有效期 | 获取方式 |\n|----------|----------|----------|--------|----------|\n| 新用户自动折扣 | 首月8折 | 新注册用户 | 长期有效 | 注册后自动显示在结算页 |\n| 套餐限时直降 | 部分套餐8折 | 所有用户 | 2026-06-19至2026-07-19 | 官网活动页面领取 |\n| 老用户回馈 | 续费8折 | 已付费用户 | 不定期 | 通过邮件或站内信发放 |\n\n> 注意：具体折扣比例和适用套餐以官网实际显示为准。\n\n## 适用人群\n\n- **新用户**：首次注册IPLC机场，可享受自动折扣，无需优惠码。\n- **需要长期稳定的用户**：适合选择年付套餐，叠加限时直降活动更划算。\n- **老用户**：关注邮箱或站内通知，及时领取专属续费优惠。\n\n## 使用步骤\n\n1. **访问官网**：打开IPLC机场官方网站（请认准官方域名，避免钓鱼网站）。\n2. **注册/登录**：新用户需注册账号，老用户直接登录。\n3. **选择套餐**：在套餐页面挑选适合的订阅计划，注意活动标签。\n4. **输入优惠码**：如有优惠码，在结算页的“优惠码”输入框中填写。\n5. **核验折扣**：确认订单金额已变为8折后再支付。\n6. **完成支付**：支持支付宝、微信或加密货币等方式。\n\n## 核验方法\n\n1. **结算页核验**：在支付前，仔细检查订单总价是否已应用折扣。\n2. **优惠码反馈**：输入优惠码后，页面会提示“优惠码有效”或显示折扣金额，若无提示则可能无效。\n3. **联系客服**：若折扣未生效，可联系在线客服确认活动是否过期。\n\n## 常见失败原因\n\n- **优惠码已过期**：部分优惠码有时效性，超过有效期后无法使用。\n- **不满足使用条件**：例如仅限新用户、仅限特定套餐等。\n- **输入错误**：注意大小写和特殊字符，建议直接复制粘贴。\n- **活动名额已满**：部分限时活动有名额限制，先到先得。\n- **账号已使用过**：同一账号可能只能享受一次新用户优惠。\n\n## 领取/下单前检查清单\n\n- [ ] 确认官网地址正确，无拼写错误。\n- [ ] 已注册并登录账号。\n- [ ] 确认所选套餐参与活动。\n- [ ] 准备好优惠码（如有）。\n- [ ] 结算页确认折扣已应用。\n- [ ] 支付方式可用。\n\n## 风险提醒\n\n- 请通过官方渠道获取优惠码，避免轻信非官方来源的“内部码”，以防被骗。\n- 折扣活动可能随时调整，以官网最新公告为准。\n- 支付前务必核验折扣，支付后不予补差。\n- 建议保留订单截图，作为后续维权凭证。\n\n## 更新说明\n\n本文最后更新于2026-06-19。优惠信息具有时效性，若发现内容过期，请通过评论区反馈。我们将持续跟踪最新活动并及时更新。",
  "faq": [
    {
      "question": "IPLC机场现在有8折优惠码吗？",
      "answer": "截至2026年6月19日，暂未确认到可公开验证的固定优惠码。但新用户注册后通常自动享受首月8折，部分套餐也有限时直降活动，建议直接在官网结算页查看。"
    },
    {
      "question": "如何获取IPLC机场的优惠码？",
      "answer": "可以通过关注官网公告、订阅邮件通知或加入官方社群获取。新用户无需优惠码，注册后自动显示折扣；老用户留意站内信或邮箱的专属优惠。"
    },
    {
      "question": "为什么我输入优惠码后没有折扣？",
      "answer": "可能原因：优惠码已过期、不满足使用条件（如仅限新用户或特定套餐）、输入错误、活动名额已满或账号已使用过。建议核对后重试或联系客服。"
    },
    {
      "question": "IPLC机场的8折活动持续到什么时候？",
      "answer": "目前已知的套餐限时直降活动有效期至2026年7月19日，但新用户自动折扣长期有效。具体以官网实际显示为准。"
    }
  ],
  "date": "2026-06-19",
  "slug": "iplc-8-1ffedfa9",
  "image": "/assets/img/paoluzyun-hero.png"
}
